<?xml version="1.0" encoding="utf-8"?>
<Resources Culture="en-US">
	<Group Type="String">
		<Items>
			<Item Name="LocalizableStrings.DuplicatesActionCaptionPattern.Value" Value="Show duplicate '{0}'" />
			<Item Name="LocalizableStrings.FillAccountWithSocialNetworksDataActionCaption.Value" Value="Update with social networks data" />
			<Item Name="LocalizableStrings.GenerateReportWithoutFiltersConfirmationMessage.Value" Value="The report will be generated for all records in the section, without filters. Do you wish to proceed?" />
			<Item Name="LocalizableStrings.SubscribeCaption.Value" Value="Follow the feed" />
			<Item Name="LocalizableStrings.UnsubscribeCaption.Value" Value="Unfollow the feed" />
		</Items>
	</Group>
</Resources>